m2py/__init__.py
m2py/segmentation/__init__.py
m2py/segmentation/persistence_watershed_algorithm.py
m2py/segmentation/segmentation_gmm.py
m2py/segmentation/segmentation_watershed.py
m2py/utils/__init__.py
m2py/utils/config.py
m2py/utils/post_processing.py
m2py/utils/pre_processing.py
m2py/utils/seg_label_utils.py
m2py/utils/utils.py
m2py-0.0.4.dist-info/LICENSE
m2py-0.0.4.dist-info/METADATA
m2py-0.0.4.dist-info/WHEEL
m2py-0.0.4.dist-info/top_level.txt
m2py-0.0.4.dist-info/RECORD
