Metadata-Version: 2.1
Name: m2py
Version: 0.0.4
Summary: Materials Morphology Python Package
Home-page: https://github.com/ponl/m2py
Author: Diego Torrejon
Author-email: diego.torrejon.medina@gmail.com
License: UNKNOWN
Platform: UNKNOWN
Classifier: Programming Language :: Python :: 3
Classifier: License :: OSI Approved :: Apache Software License
Classifier: Operating System :: OS Independent
Requires-Python: >=3.6
Requires-Dist: matplotlib (==2.2.3)
Requires-Dist: numpy (==1.15.1)
Requires-Dist: scipy (==1.1.0)
Requires-Dist: sklearn (==0.0)
Requires-Dist: scikit-image (==0.16.2)
